karaoke_generator/__init__.py
karaoke_generator/generator.py
karaoke_generator/utils/__init__.py
karaoke_generator/utils/cli.py
karaoke_video_generator-0.3.0.dist-info/METADATA
karaoke_video_generator-0.3.0.dist-info/WHEEL
karaoke_video_generator-0.3.0.dist-info/entry_points.txt
karaoke_video_generator-0.3.0.dist-info/RECORD
