Metadata-Version: 2.1
Name: karaoke-video-generator
Version: 0.3.0
Summary: Fully automated creation of _acceptable_ karaoke music videos from any music on YouTube, using open source tools and AI (e.g. Whisper and MDX-Net)
License: MIT
Author: Andrew Beveridge
Author-email: andrew@beveridge.uk
Requires-Python: >=3.9,<3.11
Classifier: License :: OSI Approved :: MIT License
Classifier: Programming Language :: Python :: 3
Classifier: Programming Language :: Python :: 3.9
Classifier: Programming Language :: Python :: 3.10
Requires-Dist: audio-separator (>=0,<1)
Requires-Dist: lyrics-transcriber (>=0.5.1,<0.6.0)
Requires-Dist: pydub (>=0.25.1,<0.26.0)
Requires-Dist: python-slugify (>=8.0.1,<9.0.0)
Requires-Dist: regex (>=2023.6.3,<2024.0.0)
Requires-Dist: yt-dlp (>=2023.6.22,<2024.0.0)
